bivario/__init__.py
bivario/_alpha.py
bivario/_constants.py
bivario/_scheme.py
bivario/cmap.py
bivario/example_data/__init__.py
bivario/example_data/nyc_bike_trips.csv.gz
bivario/folium/__init__.py
bivario/folium/_legend.py
bivario/legend.py
bivario/lonboard/__init__.py
bivario/palettes.py
bivario/py.typed
bivario/typing.py
bivario-0.3.1.dist-info/WHEEL
bivario-0.3.1.dist-info/METADATA
bivario-0.3.1.dist-info/RECORD
