Metadata-Version: 2.3
Name: bivario
Version: 0.3.1
Summary: Python library for plotting bivariate choropleth maps
Author: Kamil Raczycki
Author-email: Kamil Raczycki <kraczycki@kraina.ai>
License: MIT
Classifier: Development Status :: 3 - Alpha
Classifier: License :: OSI Approved :: MIT License
Classifier: Topic :: Scientific/Engineering :: GIS
Classifier: Intended Audience :: Science/Research
Classifier: Intended Audience :: Developers
Classifier: Programming Language :: Python :: 3
Classifier: Programming Language :: Python :: 3.10
Classifier: Programming Language :: Python :: 3.11
Classifier: Programming Language :: Python :: 3.12
Classifier: Programming Language :: Python :: 3.13
Classifier: Operating System :: Unix
Classifier: Operating System :: MacOS
Classifier: Operating System :: Microsoft :: Windows
Requires-Dist: colour-science>=0.4.0
Requires-Dist: mapclassify>=2
Requires-Dist: matplotlib>=3.3
Requires-Dist: narwhals>=1.9.4
Requires-Dist: numpy>=1.19
Requires-Python: >=3.10
Project-URL: Changelog, https://github.com/RaczeQ/bivario/blob/main/CHANGELOG.md
Project-URL: Homepage, https://github.com/RaczeQ/bivario
Project-URL: Repository, https://github.com/RaczeQ/bivario
